{
  "id": "d2_q9",
  "type": "single",
  "text": "Amazon Comprehendが提供する機能として正しくないものはどれですか？",
  "choices": [
    {
      "label": "A",
      "text": "感情分析"
    },
    {
      "label": "B",
      "text": "エンティティ認識"
    },
    {
      "label": "C",
      "text": "音声からテキストへの変換"
    },
    {
      "label": "D",
      "text": "キーフレーズ抽出"
    }
  ],
  "correct": [
    2
  ],
  "explanation": "<h5>詳細解説</h5><p>Amazon Comprehendは自然言語処理（NLP）サービスで、テキスト分析に特化しています。正解はC「音声からテキストへの変換」で、これはComprehendが提供しない機能です。</p><h5>Amazon Comprehendが提供する機能</h5><ul><li>A: 感情分析 - テキストのポジティブ/ネガティブ/ニュートラル/混合を判定</li><li>B: エンティティ認識 - 人名、場所、日付、組織などを抽出</li><li>D: キーフレーズ抽出 - テキストから重要なフレーズを抽出</li></ul><h5>その他のComprehendの機能</h5><ul><li>言語検出</li><li>トピックモデリング</li><li>カスタム分類</li><li>PII（個人識別情報）の検出とマスキング</li></ul><p>音声からテキストへの変換はAmazon Transcribeの機能です。Comprehendはテキストデータを入力として受け取り、その分析を行います。</p><h5>なぜ他の選択肢が間違っているのか</h5><ul><li><strong>A) 感情分析:</strong> 感情分析 - テキストのポジティブ/ネガティブ/ニュートラル/混合を判定</li><li><strong>B) エンティティ認識:</strong> エンティティ認識 - 人名、場所、日付、組織などを抽出</li><li><strong>D) キーフレーズ抽出:</strong> キーフレーズ抽出 - テキストから重要なフレーズを抽出</li></ul>",
  "resources": []
}