{
  "id": "d3_q35",
  "type": "single",
  "text": "「子供向けAIサービス」を開発する際の特別な配慮事項はどれですか？",
  "choices": [
    {
      "label": "A",
      "text": "大人と同じ扱いで問題ない"
    },
    {
      "label": "B",
      "text": "年齢確認、保護者の同意、教育的価値、有害コンテンツフィルタリング"
    },
    {
      "label": "C",
      "text": "より多くの広告を表示する"
    },
    {
      "label": "D",
      "text": "プライバシー保護を緩和する"
    }
  ],
  "correct": [
    1
  ],
  "explanation": "正解はB「年齢確認、保護者の同意、教育的価値、有害コンテンツフィルタリング」です。\n\n子供向けAIサービスの開発には、子供の発達段階、脆弱性、特別な保護の必要性を考慮した特別な配慮が必要です。多くの国では、子供のオンラインプライバシーを保護する特別な法律（COPPA、GDPRなど）が存在します。\n\n特別な配慮事項：\n\n1. 年齢確認：\n- 適切な年齢確認メカニズムの実装\n- 年齢に応じた機能制限\n- 発達段階に適したインターフェース\n\n2. 保護者の同意：\n- 13歳未満（多くの法域）での保護者の明示的同意\n- 保護者による管理機能\n- データ収集と使用に関する透明性\n\n3. 教育的価値：\n- 学習と発達を促進する内容\n- 年齢に適した教育コンテンツ\n- 健全な使用習慣の促進\n- スクリーンタイムの管理\n\n4. 有害コンテンツフィルタリング：\n- 不適切なコンテンツの自動検出と除去\n- いじめや搾取からの保護\n- 安全なコミュニケーション環境\n- 緊急時の報告メカニズム\n\n他の選択肢が不適切な理由：\n- A「大人と同じ扱いで問題ない」：子供は特別な保護を必要とする脆弱なグループです。\n- C「より多くの広告を表示する」：子供を商業的搾取から保護する必要があります。\n- D「プライバシー保護を緩和する」：子供のプライバシーはより厳格に保護されるべきです。\n\n子供の最善の利益を最優先に考えた設計が不可欠です。",
  "resources": []
}